{
  "_class": "shapeGroup",
  "clippingMaskMode": 0,
  "do_objectID": "826FF4E9-563C-4EA7-9992-438FB334F501",
  "exportOptions": {
    "_class": "exportOptions",
    "do_objectID": "1641B123-B99A-4A7F-9415-3CC47B736C48",
    "exportFormats": [
    ],
    "includedLayerIds": [
    ],
    "layerOptions": 0,
    "shouldTrim": false
  },
  "frame": {
    "_class": "rect",
    "constrainProportions": true,
    "do_objectID": "9E6FA9C9-99FC-46E4-9AD7-4546662E4D21",
    "height": 84.00150000000001,
    "width": 72,
    "x": 30,
    "y": 34
  },
  "hasClickThrough": false,
  "hasClippingMask": false,
  "isFlippedHorizontal": false,
  "isFlippedVertical": false,
  "isLocked": false,
  "isVisible": true,
  "layerListExpandedType": 1,
  "layers": [
    {
      "class": "shapePath",
      "id": "842DE01E-0553-4D8F-814C-69F98A68A32D"
    }
  ],
  "name": "Shape",
  "nameIsFixed": false,
  "resizingConstraint": 63,
  "resizingType": 0,
  "rotation": 0,
  "shouldBreakMaskChain": false,
  "style": {
    "_class": "style",
    "do_objectID": "662E330B-E5AB-4050-9D49-448853349B95",
    "endDecorationType": 0,
    "fills": [
      {
        "_class": "fill",
        "color": {
          "_class": "color",
          "alpha": 1,
          "blue": 0.9882352941176471,
          "green": 0.5372549019607844,
          "red": 0.09019607843137256
        },
        "fillType": 0,
        "isEnabled": true,
        "noiseIndex": 0,
        "noiseIntensity": 0,
        "patternFillType": 1,
        "patternTileScale": 1
      }
    ],
    "miterLimit": 10,
    "startDecorationType": 0
  },
  "userInfo": {
    "com.animaapp.stc-sketch-plugin": {
      "kModelPropertiesKey": {
        "constraints": {
          "aspectRatio": {
            "constant": 84.0015,
            "enabled": 1,
            "modelID": "constraint_1cb4987e-7a94-4b77-888d-df896e88a77d",
            "model_class": "ADModelConstraint",
            "model_version": 0.1,
            "multiplier": 72
          },
          "automatic": 1,
          "modelID": "viewConstraints_5de0dbf4-dea4-401c-b838-cef6473c2dd7",
          "model_class": "ADModelViewConstraints",
          "model_version": 0.1,
          "scaleFactor": 1
        }
      }
    }
  },
  "windingRule": 0
}