{
  "_class": "shapeGroup",
  "clippingMaskMode": 0,
  "do_objectID": "BB82B04B-398B-4FB2-BA1E-90A52A918C3C",
  "exportOptions": {
    "_class": "exportOptions",
    "do_objectID": "A0457A11-4DF6-4B75-8133-C785D30C9166",
    "exportFormats": [
    ],
    "includedLayerIds": [
    ],
    "layerOptions": 0,
    "shouldTrim": false
  },
  "frame": {
    "_class": "rect",
    "constrainProportions": false,
    "do_objectID": "C38055EE-7A68-4AD1-8D6E-1B6B60E81948",
    "height": 4,
    "width": 22,
    "x": 694,
    "y": 2247
  },
  "hasClickThrough": false,
  "hasClippingMask": false,
  "isFlippedHorizontal": false,
  "isFlippedVertical": false,
  "isLocked": false,
  "isVisible": true,
  "layerListExpandedType": 0,
  "layers": [
    {
      "class": "shapePath",
      "id": "8C720781-EF22-4788-9CBB-8F275BB665B5"
    }
  ],
  "name": "Path 2 Copy 5",
  "nameIsFixed": false,
  "resizingConstraint": 63,
  "resizingType": 0,
  "rotation": 0,
  "shouldBreakMaskChain": false,
  "style": {
    "_class": "style",
    "borderOptions": {
      "_class": "borderOptions",
      "dashPattern": [
      ],
      "do_objectID": "B2981546-5756-4E50-9C69-FF5D5468FE40",
      "isEnabled": false,
      "lineCapStyle": 2,
      "lineJoinStyle": 0
    },
    "borders": [
      {
        "_class": "border",
        "color": {
          "_class": "color",
          "alpha": 1,
          "blue": 0.9841268105817158,
          "green": 0.9883343962585034,
          "red": 0.9760699088996295
        },
        "fillType": 0,
        "isEnabled": true,
        "position": 0,
        "thickness": 4
      }
    ],
    "do_objectID": "4A736DCC-6C23-4FB0-96BF-AB407730BB8A",
    "endDecorationType": 0,
    "fills": [
      {
        "_class": "fill",
        "color": {
          "_class": "color",
          "alpha": 1,
          "blue": 0.847,
          "green": 0.847,
          "red": 0.847
        },
        "fillType": 0,
        "isEnabled": false,
        "noiseIndex": 0,
        "noiseIntensity": 0,
        "patternFillType": 0,
        "patternTileScale": 1
      }
    ],
    "miterLimit": 10,
    "startDecorationType": 0
  },
  "windingRule": 1
}