{
  "_class": "shapePath",
  "booleanOperation": -1,
  "do_objectID": "CE1A03CC-8F3D-4FCA-B61F-C9B6DC81ABDD",
  "edited": true,
  "exportOptions": {
    "_class": "exportOptions",
    "do_objectID": "67EC552F-467A-4C15-ACCF-346ED3575CA1",
    "exportFormats": [
    ],
    "includedLayerIds": [
    ],
    "layerOptions": 0,
    "shouldTrim": false
  },
  "frame": {
    "_class": "rect",
    "constrainProportions": false,
    "do_objectID": "7FF8B332-99AE-4371-8BB8-DD6D6F89A9AB",
    "height": 30.024,
    "width": 30.024,
    "x": 0,
    "y": 0
  },
  "isClosed": true,
  "isFlippedHorizontal": false,
  "isFlippedVertical": false,
  "isLocked": false,
  "isVisible": true,
  "layerListExpandedType": 0,
  "name": "Path",
  "nameIsFixed": false,
  "path": {
    "_class": "path",
    "isClosed": true,
    "pointRadiusBehaviour": 1,
    "points": [
      {
        "_class": "curvePoint",
        "cornerRadius": 0,
        "curveFrom": "{0.22435385025313095, 1}",
        "curveMode": 2,
        "curveTo": "{0.77564614974686907, 1}",
        "hasCurveFrom": true,
        "hasCurveTo": true,
        "point": "{0.5, 1}"
      },
      {
        "_class": "curvePoint",
        "cornerRadius": 0,
        "curveFrom": "{0, 0.2242539301891821}",
        "curveMode": 2,
        "curveTo": "{0, 0.77557953637090327}",
        "hasCurveFrom": true,
        "hasCurveTo": true,
        "point": "{0, 0.5}"
      },
      {
        "_class": "curvePoint",
        "cornerRadius": 0,
        "curveFrom": "{0.77567945643485214, 0}",
        "curveMode": 2,
        "curveTo": "{0.22432054356514786, 0}",
        "hasCurveFrom": true,
        "hasCurveTo": true,
        "point": "{0.5, 0}"
      },
      {
        "_class": "curvePoint",
        "cornerRadius": 0,
        "curveFrom": "{0.99996669331201693, 0.77557953637090327}",
        "curveMode": 2,
        "curveTo": "{1, 0.22422062350119901}",
        "hasCurveFrom": true,
        "hasCurveTo": true,
        "point": "{1, 0.5}"
      }
    ]
  },
  "pointRadiusBehaviour": 1,
  "points": [
    {
      "_class": "curvePoint",
      "cornerRadius": 0,
      "curveFrom": "{0.22435385025313095, 1}",
      "curveMode": 2,
      "curveTo": "{0.77564614974686907, 1}",
      "hasCurveFrom": true,
      "hasCurveTo": true,
      "point": "{0.5, 1}"
    },
    {
      "_class": "curvePoint",
      "cornerRadius": 0,
      "curveFrom": "{0, 0.2242539301891821}",
      "curveMode": 2,
      "curveTo": "{0, 0.77557953637090327}",
      "hasCurveFrom": true,
      "hasCurveTo": true,
      "point": "{0, 0.5}"
    },
    {
      "_class": "curvePoint",
      "cornerRadius": 0,
      "curveFrom": "{0.77567945643485214, 0}",
      "curveMode": 2,
      "curveTo": "{0.22432054356514786, 0}",
      "hasCurveFrom": true,
      "hasCurveTo": true,
      "point": "{0.5, 0}"
    },
    {
      "_class": "curvePoint",
      "cornerRadius": 0,
      "curveFrom": "{0.99996669331201693, 0.77557953637090327}",
      "curveMode": 2,
      "curveTo": "{1, 0.22422062350119901}",
      "hasCurveFrom": true,
      "hasCurveTo": true,
      "point": "{1, 0.5}"
    }
  ],
  "resizingConstraint": 63,
  "resizingType": 0,
  "rotation": 0,
  "shouldBreakMaskChain": false
}