{
  "_class": "group",
  "do_objectID": "CFD42487-B00A-404D-A1CA-789C9E05B7F7",
  "exportOptions": {
    "_class": "exportOptions",
    "exportFormats": [
    ],
    "includedLayerIds": [
    ],
    "layerOptions": 0,
    "shouldTrim": false
  },
  "frame": {
    "_class": "rect",
    "constrainProportions": false,
    "height": 113,
    "width": 123,
    "x": 0,
    "y": 0
  },
  "hasClickThrough": false,
  "isFlippedHorizontal": false,
  "isFlippedVertical": false,
  "isLocked": false,
  "isVisible": true,
  "layerListExpandedType": 0,
  "layers": [
    {
      "class": "group",
      "id": "226E9122-06AE-4A1D-843A-CE4DF25DBC6C"
    },
    {
      "class": "shapeGroup",
      "id": "1B7750EA-74FE-432F-9E5E-15BDBDBE97C9"
    },
    {
      "class": "shapeGroup",
      "id": "FCB99718-A4CE-4265-AE7E-0321D5C90F8A"
    }
  ],
  "name": "Group 8",
  "nameIsFixed": false,
  "resizingConstraint": 63,
  "resizingType": 0,
  "rotation": 0,
  "shouldBreakMaskChain": false,
  "style": {
    "_class": "style",
    "endDecorationType": 0,
    "miterLimit": 10,
    "startDecorationType": 0
  },
  "userInfo": {
    "com.animaapp.stc-sketch-plugin": {
      "kModelPropertiesKey": {
      }
    }
  }
}